{
  "kind": "collectionType",
  "collectionName": "info_blogs",
  "info": {
    "singularName": "info-blog",
    "pluralName": "info-blogs",
    "displayName": "Info blog",
    "description": ""
  },
  "options": {
    "draftAndPublish": true
  },
  "pluginOptions": {
    "i18n": {
      "localized": true
    }
  },
  "attributes": {
    "Titulo": {
      "pluginOptions": {
        "i18n": {
          "localized": true
        }
      },
      "type": "string",
      "required": true,
      "maxLength": 150,
      "minLength": 1
    },
    "launch": {
      "pluginOptions": {
        "i18n": {
          "localized": true
        }
      },
      "type": "date",
      "required": true
    },
    "description": {
      "pluginOptions": {
        "i18n": {
          "localized": true
        }
      },
      "type": "blocks",
      "required": true
    },
    "cover": {
      "type": "media",
      "multiple": false,
      "required": false,
      "allowedTypes": [
        "images"
      ],
      "pluginOptions": {
        "i18n": {
          "localized": true
        }
      }
    },
    "slug": {
      "pluginOptions": {
        "i18n": {
          "localized": true
        }
      },
      "type": "uid",
      "targetField": "Titulo"
    },
    "platforms": {
      "type": "relation",
      "relation": "manyToMany",
      "target": "api::platform.platform",
      "inversedBy": "info_blogs"
    }
  }
}
